{
  "fetched_at": "2026-04-13T12:29:10.968687Z",
  "source": "Harris County Clerk - Foreclosure Postings (cclerk.hctx.net)",
  "target_months": [
    "May 2026",
    "June 2026",
    "July 2026"
  ],
  "total": 60,
  "with_address": 20,
  "records": [
    {
      "doc_id": "FRCL-2026-612",
      "doc_type": "FRCL",
      "cat": "FORECLOSURE",
      "cat_label": "Foreclosure Posting",
      "sale_date": "05/05/2026",
      "file_date": "01/22/2026",
      "date_scraped": "2026-04-13",
      "batch_id": "B1",
      "batch_label": "Batch 1 \u2014 2026-04-13 02:58 AM",
      "grantor": "",
      "co_borrower": "",
      "amount": "",
      "mortgagee": "",
      "legal_description": "",
      "prop_address": "Not found",
      "prop_city": "",
      "prop_state": "TX",
      "prop_zip": "",
      "match_confidence": "none",
      "hcad_url": "",
      "clerk_url": "https://www.cclerk.hctx.net/applications/websearch/ViewECdocs.aspx?ID=bWXqGXasMeuE7YZXR3B2NSvzTel3b4phRC1xP2A+jyuSmanaDQZ2Csd7gRIyOLCWG1VYDcRkWZ8xT7b3r5QPSmK2HI23/Rnq2QEVXR9iPg08WQj46tLelVYmz6iuuq6F",
      "needs_ocr": false
    },
    {
      "doc_id": "FRCL-2026-1157",
      "doc_type": "FRCL",
      "cat": "FORECLOSURE",
      "cat_label": "Foreclosure Posting",
      "sale_date": "05/05/2026",
      "file_date": "02/12/2026",
      "date_scraped": "2026-04-13",
      "batch_id": "B1",
      "batch_label": "Batch 1 \u2014 2026-04-13 02:58 AM",
      "grantor": "by MAXINE ELAINE ALABI",
      "co_borrower": "",
      "amount": "$408,165.00",
      "mortgagee": "PLANET HOME LENDING",
      "legal_description": "as follows: \"dy 4 | . o LOT TWENTY-NINE (29), IN BLOCK TO (2), OF BALMORAL SEC = TWENTY-FIVE (25), A SUBDIVISION IW HARRIS SOUNTY, TEXAS, 2 ACCORDING: TO THE MAP OR PLAT THBREOF BBCORDED UNDER | es FILM CODE NO. 694829 OF THE MAP RECORDING IARRIS COUNTY, I TEX AS. SS O a : 5 '",
      "prop_address": "15647 COUNTESSWELLS DRIVE",
      "prop_city": "HUMBLE",
      "prop_state": "TX",
      "prop_zip": "77346",
      "match_confidence": "high",
      "hcad_url": "",
      "clerk_url": "https://www.cclerk.hctx.net/applications/websearch/ViewECdocs.aspx?ID=bWXqGXasMeuE7YZXR3B2NUNXeLVZTKlhHSbKofnpRC4ahyu26ICdJzacx37TkQfbeyLMniN3YugKOBCXxw9Nf6N2DJA4ZQMQYE+665/cAuKRbx/a4U/WBxF0MiNelRb1",
      "needs_ocr": false
    },
    {
      "doc_id": "FRCL-2026-1158",
      "doc_type": "FRCL",
      "cat": "FORECLOSURE",
      "cat_label": "Foreclosure Posting",
      "sale_date": "05/05/2026",
      "file_date": "02/12/2026",
      "date_scraped": "2026-04-13",
      "batch_id": "B1",
      "batch_label": "Batch 1 \u2014 2026-04-13 02:58 AM",
      "grantor": "MAYORGA",
      "co_borrower": "",
      "amount": "",
      "mortgagee": "LAKEVIEW LOAN SERVICING",
      "legal_description": "as follows: oc . . o LOT EIGHTEEN (18), IN BLOCK THREE (3), OF KATY TRAILS, SEC2,A - SUBDIVISION IN HARRIS COUNTY",
      "prop_address": "23422 DOVETAIL COLONY CT",
      "prop_city": "KATY",
      "prop_state": "TX",
      "prop_zip": "77493",
      "match_confidence": "high",
      "hcad_url": "",
      "clerk_url": "https://www.cclerk.hctx.net/applications/websearch/ViewECdocs.aspx?ID=bWXqGXasMeuE7YZXR3B2NUNXeLVZTKlhHSbKofnpRC6zjX01qzqSjrkkPY7m5zRb2gOdoUiqwcaiQkbemvu4QNqLfllhqUhLI6zrhFhPiN32GlwUngLVz3Mf1XvUlNXP",
      "needs_ocr": false
    },
    {
      "doc_id": "FRCL-2026-1159",
      "doc_type": "FRCL",
      "cat": "FORECLOSURE",
      "cat_label": "Foreclosure Posting",
      "sale_date": "05/05/2026",
      "file_date": "02/12/2026",
      "date_scraped": "2026-04-13",
      "batch_id": "B1",
      "batch_label": "Batch 1 \u2014 2026-04-13 02:58 AM",
      "grantor": "James B Kerchner, Sr",
      "co_borrower": "",
      "amount": "$135,751.00",
      "mortgagee": "Carrington\nN Mortgage Services, LLC, which is the mortgagee of the Note and Deed of Trust or mortgage and the legal holder of",
      "legal_description": "Lot Twenty-three (23), in Block Two (2), of Mallard Crossing Sec. 2, a Subdivision in Harris County",
      "prop_address": "24 GRA YBitily COURT",
      "prop_city": "HOCKLEY",
      "prop_state": "TX",
      "prop_zip": "77447",
      "match_confidence": "high",
      "hcad_url": "",
      "clerk_url": "https://www.cclerk.hctx.net/applications/websearch/ViewECdocs.aspx?ID=bWXqGXasMeuE7YZXR3B2NUNXeLVZTKlhHSbKofnpRC5ErekRJTxoDULsC7IXffpxfCaIBeCKMWMQQ3HywCxoC+twXR7p9yddx0pri7BIESEuhQ0BU5zZAvEbErY3gm9Y",
      "needs_ocr": false
    },
    {
      "doc_id": "FRCL-2026-1160",
      "doc_type": "FRCL",
      "cat": "FORECLOSURE",
      "cat_label": "Foreclosure Posting",
      "sale_date": "05/05/2026",
      "file_date": "02/12/2026",
      "date_scraped": "2026-04-13",
      "batch_id": "B1",
      "batch_label": "Batch 1 \u2014 2026-04-13 02:58 AM",
      "grantor": "",
      "co_borrower": "",
      "amount": "$253,326.00",
      "mortgagee": "",
      "legal_description": "Lot Thirty-Eight (38), in Block Six (6), of Highland Acre Home: s > Annex No. Five (5), a subdivision in Harris a. County, Texas",
      "prop_address": "2470 CLIFFDALE ST",
      "prop_city": "HOUSTON",
      "prop_state": "TX",
      "prop_zip": "77091",
      "match_confidence": "high",
      "hcad_url": "",
      "clerk_url": "https://www.cclerk.hctx.net/applications/websearch/ViewECdocs.aspx?ID=bWXqGXasMeuE7YZXR3B2NUNXeLVZTKlhHSbKofnpRC7Hq/N+hTHL490RdyZuIAlSuR8n9h2IRSooqHtgN9Asfv8IqklmtAXocH1vDTyB4QCdyVUedgAlGzaXQ5guBXJT",
      "needs_ocr": false
    },
    {
      "doc_id": "FRCL-2026-1171",
      "doc_type": "FRCL",
      "cat": "FORECLOSURE",
      "cat_label": "Foreclosure Posting",
      "sale_date": "05/05/2026",
      "file_date": "02/12/2026",
      "date_scraped": "2026-04-13",
      "batch_id": "B1",
      "batch_label": "Batch 1 \u2014 2026-04-13 02:58 AM",
      "grantor": "",
      "co_borrower": "",
      "amount": "$236,568.00",
      "mortgagee": "authorized to represent the Mortgagee by virtue of a\n\na servicing agreement with the Mortgagee",
      "legal_description": "LOT THIRTY-ONE (31), IN BLOCK TWENTY-NINE (29), OF $SEMON? SECTION SIX (6), A SUBDIVISION IN HARRIS ~ Oo COUNTY, TEXAS",
      "prop_address": "5 HOUST",
      "prop_city": "ON",
      "prop_state": "TX",
      "prop_zip": "77089",
      "match_confidence": "high",
      "hcad_url": "",
      "clerk_url": "https://www.cclerk.hctx.net/applications/websearch/ViewECdocs.aspx?ID=bWXqGXasMeuE7YZXR3B2NdRpQgMQd0Nsa06X5vPrNVSKBjVsOQn0m5v4Opzg4O53Up0PG/auyfMgPcAjzYUFiK8aeRMbioGKbbt1f1MzYXt3d2UjjubuZnM11KZYtZ+q",
      "needs_ocr": false
    },
    {
      "doc_id": "FRCL-2026-1172",
      "doc_type": "FRCL",
      "cat": "FORECLOSURE",
      "cat_label": "Foreclosure Posting",
      "sale_date": "05/05/2026",
      "file_date": "02/12/2026",
      "date_scraped": "2026-04-13",
      "batch_id": "B1",
      "batch_label": "Batch 1 \u2014 2026-04-13 02:58 AM",
      "grantor": "",
      "co_borrower": "",
      "amount": "$4",
      "mortgagee": "",
      "legal_description": "LOT THIRTY (30), BLOCK ONE (1), OF gi@fffMliigzs OF CYPRESS LAKES, SECTION NINE (9), A SUBDIVISION IN HARRIS 5 COUNTY, TEXAS",
      "prop_address": "15514 HICKORY DALE ST",
      "prop_city": "CYPRESS",
      "prop_state": "TX",
      "prop_zip": "77429",
      "match_confidence": "high",
      "hcad_url": "",
      "clerk_url": "https://www.cclerk.hctx.net/applications/websearch/ViewECdocs.aspx?ID=bWXqGXasMeuE7YZXR3B2NdRpQgMQd0Nsa06X5vPrNVSvCznyVl7MF/sZmR99xOa+GNvJ2bM51mtaeTWbmjzshrs6ykElbgBG2QXahVOPp6ztTQ6vp3ZlgdSmqbtcpA42",
      "needs_ocr": false
    },
    {
      "doc_id": "FRCL-2026-1165",
      "doc_type": "FRCL",
      "cat": "FORECLOSURE",
      "cat_label": "Foreclosure Posting",
      "sale_date": "05/05/2026",
      "file_date": "02/12/2026",
      "date_scraped": "2026-04-13",
      "batch_id": "B1",
      "batch_label": "Batch 1 \u2014 2026-04-13 02:58 AM",
      "grantor": "",
      "co_borrower": "",
      "amount": "",
      "mortgagee": "",
      "legal_description": "WW DESIGNATED BY THE COUNTY COMMISSIONERS OFFICE OR IN THE AREA DESIGNATED BY THE COMMISSIONER'S COURT, O PURSUANT TO SECTION 51.002 OF THE TEXAS PROPERTY CODE. > 5 Legal Description: LEGAL DESCRIPTION ATTACHED AS EXHIBIT A 5 In accordance with TEx. PROP. CODE \u00a751.0076 and the",
      "prop_address": "Not found",
      "prop_city": "",
      "prop_state": "TX",
      "prop_zip": "",
      "match_confidence": "none",
      "hcad_url": "",
      "clerk_url": "https://www.cclerk.hctx.net/applications/websearch/ViewECdocs.aspx?ID=bWXqGXasMeuE7YZXR3B2NUNXeLVZTKlhHSbKofnpRC7KVyLlKw4FH+E2cCw0SRlTEPUF9NxMWtOS4y58vuXsI4G3uTONJvO2orDyi9DsYoTCdPdDMJDMaV9Zrhosw1tt",
      "needs_ocr": false
    },
    {
      "doc_id": "FRCL-2026-1178",
      "doc_type": "FRCL",
      "cat": "FORECLOSURE",
      "cat_label": "Foreclosure Posting",
      "sale_date": "05/05/2026",
      "file_date": "02/12/2026",
      "date_scraped": "2026-04-13",
      "batch_id": "B1",
      "batch_label": "Batch 1 \u2014 2026-04-13 02:58 AM",
      "grantor": "Darees Miguel Nelson",
      "co_borrower": "Teneshia Latoya Nelson",
      "amount": "$72,242.00",
      "mortgagee": "authorized to represent the Mortgagee by virtue of a\nii servicing agreement with the Mortgagee",
      "legal_description": "LOT TWENTY FIVE (25), IN BLOCK FIVE (5), OF INWOOD FOREST, SECTION N : [EN (10), A SUBDIVISION IN HARRIS COUNTY",
      "prop_address": "7847 Antoine Dr",
      "prop_city": "Houston",
      "prop_state": "TX",
      "prop_zip": "77088",
      "match_confidence": "high",
      "hcad_url": "",
      "clerk_url": "https://www.cclerk.hctx.net/applications/websearch/ViewECdocs.aspx?ID=bWXqGXasMeuE7YZXR3B2NUNXeLVZTKlhHSbKofnpRC4VFSSJtbMwId5EDQww/cfmQk9SV7NCCtaN5c+8M6eoq55Xxv6Acd32yOUEee1d2GyOz4xWQQFCpFQjAy15MY8p",
      "needs_ocr": false
    },
    {
      "doc_id": "FRCL-2026-1197",
      "doc_type": "FRCL",
      "cat": "FORECLOSURE",
      "cat_label": "Foreclosure Posting",
      "sale_date": "05/05/2026",
      "file_date": "02/12/2026",
      "date_scraped": "2026-04-13",
      "batch_id": "B1",
      "batch_label": "Batch 1 \u2014 2026-04-13 02:58 AM",
      "grantor": "",
      "co_borrower": "",
      "amount": "",
      "mortgagee": "authorized to represent the Mortgagee by virtue of a\nce servicing agreement with the Mortgagee",
      "legal_description": "Lot Fifty (50), in Block One (1), of Northwood Pines, Sectiort. Four (4), a subdivision in Harris > County, Texas",
      "prop_address": "Not found",
      "prop_city": "",
      "prop_state": "TX",
      "prop_zip": "",
      "match_confidence": "none",
      "hcad_url": "",
      "clerk_url": "https://www.cclerk.hctx.net/applications/websearch/ViewECdocs.aspx?ID=bWXqGXasMeuE7YZXR3B2NUNXeLVZTKlhHSbKofnpRC7MTTWPV/gVhmqZRWhphRsTvywLw1HCoxB6J/aYZxMwgKQRVfhl0iiVggKgMatILyhpeoXbsP4Ey4JayzFAjd1M",
      "needs_ocr": false
    },
    {
      "doc_id": "FRCL-2026-1198",
      "doc_type": "FRCL",
      "cat": "FORECLOSURE",
      "cat_label": "Foreclosure Posting",
      "sale_date": "05/05/2026",
      "file_date": "02/12/2026",
      "date_scraped": "2026-04-13",
      "batch_id": "B1",
      "batch_label": "Batch 1 \u2014 2026-04-13 02:58 AM",
      "grantor": "",
      "co_borrower": "",
      "amount": "",
      "mortgagee": "authorized to represent the Mortgagee by virtue of a\ncc servicing agreement with the Mortgagee",
      "legal_description": "",
      "prop_address": "Not found",
      "prop_city": "",
      "prop_state": "TX",
      "prop_zip": "",
      "match_confidence": "none",
      "hcad_url": "",
      "clerk_url": "https://www.cclerk.hctx.net/applications/websearch/ViewECdocs.aspx?ID=bWXqGXasMeuE7YZXR3B2NUNXeLVZTKlhHSbKofnpRC7KM/KOU2qU3z9jHAirYy7IoGku/CJ2GwBsMl1xRPrHTYRioKQtRk8ZA1zLYoQFAk0Isx7qCAH3uS/woQYc0zf0",
      "needs_ocr": false
    },
    {
      "doc_id": "FRCL-2026-1203",
      "doc_type": "FRCL",
      "cat": "FORECLOSURE",
      "cat_label": "Foreclosure Posting",
      "sale_date": "05/05/2026",
      "file_date": "02/18/2026",
      "date_scraped": "2026-04-13",
      "batch_id": "B1",
      "batch_label": "Batch 1 \u2014 2026-04-13 02:58 AM",
      "grantor": "",
      "co_borrower": "",
      "amount": "",
      "mortgagee": "",
      "legal_description": "= ( SECTIONA6y'a subdivision in Harris County",
      "prop_address": "Not found",
      "prop_city": "",
      "prop_state": "TX",
      "prop_zip": "",
      "match_confidence": "none",
      "hcad_url": "",
      "clerk_url": "https://www.cclerk.hctx.net/applications/websearch/ViewECdocs.aspx?ID=bWXqGXasMeuE7YZXR3B2NdRpQgMQd0Nsa06X5vPrNVSx9DLfoGkE+LsMcoQfXX51fY2Hp7fCFodMrXr3PCuFCwGEKiqJAAP7vuGfJIrukPW5kqz2DFEVP6+wEIDrXMQJ",
      "needs_ocr": false
    },
    {
      "doc_id": "FRCL-2026-1247",
      "doc_type": "FRCL",
      "cat": "FORECLOSURE",
      "cat_label": "Foreclosure Posting",
      "sale_date": "05/05/2026",
      "file_date": "02/19/2026",
      "date_scraped": "2026-04-13",
      "batch_id": "B1",
      "batch_label": "Batch 1 \u2014 2026-04-13 02:58 AM",
      "grantor": "",
      "co_borrower": "",
      "amount": "",
      "mortgagee": "",
      "legal_description": "",
      "prop_address": "Not found",
      "prop_city": "",
      "prop_state": "TX",
      "prop_zip": "",
      "match_confidence": "none",
      "hcad_url": "",
      "clerk_url": "https://www.cclerk.hctx.net/applications/websearch/ViewECdocs.aspx?ID=bWXqGXasMeuE7YZXR3B2NSvzTel3b4phRC1xP2A+jytnW6PdGQcCHlCTpaQI7UlIwF4pCaSPRcxb2HukWfuTBk2Y9KBefRanwhOFLALHu5umjJAJcLcSU8uqWsn5b74h",
      "needs_ocr": false
    },
    {
      "doc_id": "FRCL-2026-1248",
      "doc_type": "FRCL",
      "cat": "FORECLOSURE",
      "cat_label": "Foreclosure Posting",
      "sale_date": "05/05/2026",
      "file_date": "02/19/2026",
      "date_scraped": "2026-04-13",
      "batch_id": "B1",
      "batch_label": "Batch 1 \u2014 2026-04-13 02:58 AM",
      "grantor": "",
      "co_borrower": "",
      "amount": "",
      "mortgagee": "",
      "legal_description": "",
      "prop_address": "Not found",
      "prop_city": "",
      "prop_state": "TX",
      "prop_zip": "",
      "match_confidence": "none",
      "hcad_url": "",
      "clerk_url": "https://www.cclerk.hctx.net/applications/websearch/ViewECdocs.aspx?ID=bWXqGXasMeuE7YZXR3B2NSvzTel3b4phRC1xP2A+jytl3bnovcTlyQfbzTUQZyi6zeTXRNrFVAXpSEWQVqKrCJc84Rp8AOI7riCfhpjVolkkJs4WFBGuWpcJhMRcppMc",
      "needs_ocr": false
    },
    {
      "doc_id": "FRCL-2026-1249",
      "doc_type": "FRCL",
      "cat": "FORECLOSURE",
      "cat_label": "Foreclosure Posting",
      "sale_date": "05/05/2026",
      "file_date": "02/19/2026",
      "date_scraped": "2026-04-13",
      "batch_id": "B1",
      "batch_label": "Batch 1 \u2014 2026-04-13 02:58 AM",
      "grantor": "",
      "co_borrower": "",
      "amount": "",
      "mortgagee": "",
      "legal_description": "",
      "prop_address": "9401 Kmight Rd",
      "prop_city": "Houston",
      "prop_state": "TX",
      "prop_zip": "77045",
      "match_confidence": "high",
      "hcad_url": "",
      "clerk_url": "https://www.cclerk.hctx.net/applications/websearch/ViewECdocs.aspx?ID=bWXqGXasMeuE7YZXR3B2NSvzTel3b4phRC1xP2A+jysHbCbvQ3sc8LHgXSllTQK5wxJmgE3iE5jw49z9Bywp35tbmwJJYFSxwl94BJh7TakWoOsxVeHS6etgiGX7xQuH",
      "needs_ocr": false
    },
    {
      "doc_id": "FRCL-2026-1275",
      "doc_type": "FRCL",
      "cat": "FORECLOSURE",
      "cat_label": "Foreclosure Posting",
      "sale_date": "05/05/2026",
      "file_date": "02/19/2026",
      "date_scraped": "2026-04-13",
      "batch_id": "B1",
      "batch_label": "Batch 1 \u2014 2026-04-13 02:58 AM",
      "grantor": "JANCA MARES",
      "co_borrower": "",
      "amount": "",
      "mortgagee": "the mortgagee",
      "legal_description": "",
      "prop_address": "Not found",
      "prop_city": "",
      "prop_state": "TX",
      "prop_zip": "",
      "match_confidence": "none",
      "hcad_url": "",
      "clerk_url": "https://www.cclerk.hctx.net/applications/websearch/ViewECdocs.aspx?ID=bWXqGXasMeuE7YZXR3B2NUNXeLVZTKlhHSbKofnpRC4yAF1U9QJAGUsVexz9ZJcoNa8aB7U65dDWZpkj0Bl4O76ntW6cEPwC+aYkVl/z6OqirhF9fvhnwNGWY4MWL8qY",
      "needs_ocr": false
    },
    {
      "doc_id": "FRCL-2026-1254",
      "doc_type": "FRCL",
      "cat": "FORECLOSURE",
      "cat_label": "Foreclosure Posting",
      "sale_date": "05/05/2026",
      "file_date": "02/19/2026",
      "date_scraped": "2026-04-13",
      "batch_id": "B1",
      "batch_label": "Batch 1 \u2014 2026-04-13 02:58 AM",
      "grantor": "ELENA PATRICIA PUENTE, AN UNMARRIED WOMAN",
      "co_borrower": "",
      "amount": "",
      "mortgagee": "",
      "legal_description": "",
      "prop_address": "Not found",
      "prop_city": "",
      "prop_state": "TX",
      "prop_zip": "",
      "match_confidence": "none",
      "hcad_url": "",
      "clerk_url": "https://www.cclerk.hctx.net/applications/websearch/ViewECdocs.aspx?ID=bWXqGXasMeuE7YZXR3B2NdRpQgMQd0Nsa06X5vPrNVQe1z/zDvxZfHmG2hpbfpvOyAAnBZNvkawdl43VR4Q7xNuezbrXntguAuEM2BKQhAOBRTBdkYUcqJkqQOMZjrji",
      "needs_ocr": false
    },
    {
      "doc_id": "FRCL-2026-1281",
      "doc_type": "FRCL",
      "cat": "FORECLOSURE",
      "cat_label": "Foreclosure Posting",
      "sale_date": "05/05/2026",
      "file_date": "02/19/2026",
      "date_scraped": "2026-04-13",
      "batch_id": "B1",
      "batch_label": "Batch 1 \u2014 2026-04-13 02:58 AM",
      "grantor": "",
      "co_borrower": "",
      "amount": "$139,428.00",
      "mortgagee": "authorized to collect the debt and to administer any resulting foreclosure of the lien securing the\nProperty referenced above",
      "legal_description": "",
      "prop_address": "Not found",
      "prop_city": "",
      "prop_state": "TX",
      "prop_zip": "",
      "match_confidence": "none",
      "hcad_url": "",
      "clerk_url": "https://www.cclerk.hctx.net/applications/websearch/ViewECdocs.aspx?ID=bWXqGXasMeuE7YZXR3B2NdRpQgMQd0Nsa06X5vPrNVRUdXRphbbNCtY+AusTeJUlD5dyIDZQd9g01NbOd3mK4Wigs+/fhyQ/GR3a4S1E2fGQxmBYI0Cge+dx0/xCXGnD",
      "needs_ocr": false
    },
    {
      "doc_id": "FRCL-2026-1282",
      "doc_type": "FRCL",
      "cat": "FORECLOSURE",
      "cat_label": "Foreclosure Posting",
      "sale_date": "05/05/2026",
      "file_date": "02/19/2026",
      "date_scraped": "2026-04-13",
      "batch_id": "B1",
      "batch_label": "Batch 1 \u2014 2026-04-13 02:58 AM",
      "grantor": "",
      "co_borrower": "",
      "amount": "$222,888.00",
      "mortgagee": "",
      "legal_description": "LOT TWENTY-FIVE (25), IN BLOCK FOUR (4), OF CREEKMONT, SECTION TWO (2), A SUBDIVISION IN HARRIS COUNTY",
      "prop_address": "Not found",
      "prop_city": "",
      "prop_state": "TX",
      "prop_zip": "",
      "match_confidence": "none",
      "hcad_url": "",
      "clerk_url": "https://www.cclerk.hctx.net/applications/websearch/ViewECdocs.aspx?ID=bWXqGXasMeuE7YZXR3B2NdRpQgMQd0Nsa06X5vPrNVT4EUcNzkRN3Gp1GJTK8SVBuYZWdkcR1ImYL/OFYGG1bQTE1ChdLEMzEN4chKUV6HzAx7c9PlcfyMrUukLMMBkl",
      "needs_ocr": false
    },
    {
      "doc_id": "FRCL-2026-1283",
      "doc_type": "FRCL",
      "cat": "FORECLOSURE",
      "cat_label": "Foreclosure Posting",
      "sale_date": "05/05/2026",
      "file_date": "02/19/2026",
      "date_scraped": "2026-04-13",
      "batch_id": "B1",
      "batch_label": "Batch 1 \u2014 2026-04-13 02:58 AM",
      "grantor": "",
      "co_borrower": "",
      "amount": "",
      "mortgagee": "",
      "legal_description": "in the attached Exhibit A. ; \u2014! e 6. Mortgage Servicer Infexmation. The Mortgage Servicer is authorized to represent the Mortgagee by virtue of a - servicing agreement witM/the Mortgagee. Pursuant to the Servicing Agreement and Texas Property Code \u00a7 51.0025, the Mortgage Servicer is @uthorized4% collect the debt and to administer any resulting foreclosure of the lien securing the Property referencgsifllMave. WELLS FARGO BANK, N.A., as Mortgage Servicer, is representing the current mortgagee, = whose address isfy yy . q 3476 STATE VAR BES\" o FORT MIL oy Oo bn ea\" ~ , Lu . \u2014 7 ; FCTX_NTSS.rpt (11/17/2020)-S Ver-03 NTSS00000010732717 _ Page Lof3 3312 ORCHID TRACE LANE 00000010732717 HOUSTON, TX 77047 | we n THIS INSTRUMENT APPOINTS THE SUBSTITUTE TRUSTEE(S) IDENTIFIED TO SELL THE PROPERTY x DESCRIBED IN",
      "prop_address": "Not found",
      "prop_city": "",
      "prop_state": "TX",
      "prop_zip": "",
      "match_confidence": "none",
      "hcad_url": "",
      "clerk_url": "https://www.cclerk.hctx.net/applications/websearch/ViewECdocs.aspx?ID=bWXqGXasMeuE7YZXR3B2NdRpQgMQd0Nsa06X5vPrNVQ+yNO3QRRhnzkPVkE0tOcWKQ9dJrJpmX7GMyaToRHidEvTuwApcVBw99+Q3nM/0Z2sVWI9bRBetjOZSNt817mM",
      "needs_ocr": false
    },
    {
      "doc_id": "FRCL-2026-1284",
      "doc_type": "FRCL",
      "cat": "FORECLOSURE",
      "cat_label": "Foreclosure Posting",
      "sale_date": "05/05/2026",
      "file_date": "02/19/2026",
      "date_scraped": "2026-04-13",
      "batch_id": "B1",
      "batch_label": "Batch 1 \u2014 2026-04-13 02:58 AM",
      "grantor": "",
      "co_borrower": "",
      "amount": "",
      "mortgagee": "",
      "legal_description": "in the attached Exhibit A. 7 2 a 6. Mortgage Servicer Information. The Mortgage Servicer 'is authorized to represent the Mortgagee by virtue of a oe servicing agreement with the Mortgagee. Pursuant to the Servicing Agreement and Texas Property Code \u00a7 51.0025, 'the _ Mortgage Servicer is authorized: to collect the debt and to administer any resulting foreclosure of the. lien securing the ~ - Property referenced above. WELLS FARGO BANK, N.A., as Mortgage Servicer, is representing the current mortgagee, \u2014 whose address is: . < c/o WELLS FARGO BANK, N.A. - . Oo, . a 3476 STATEVIEW BLVD S FORT MILL, SC 29715 | on . ' . * e wo . . 4 N . ; N i oO) 7 . a N a : . Lu . \" Wy = ; o FCTX_NTSS spt (11/17/2020)-S Ver-03 oo . NTSS00000010391415 : , Page 1 of 3 3834 MISTISSIN LANE 00000010391415 HOUSTON, TX 77053 WY) THIS INSTRUMENT APPOINTS THE SUBSTITUTE T (S) IDENTIFIED TO SELL THE PROPERTY x DESCRIBED IN",
      "prop_address": "Not found",
      "prop_city": "",
      "prop_state": "TX",
      "prop_zip": "",
      "match_confidence": "none",
      "hcad_url": "",
      "clerk_url": "https://www.cclerk.hctx.net/applications/websearch/ViewECdocs.aspx?ID=bWXqGXasMeuE7YZXR3B2NdRpQgMQd0Nsa06X5vPrNVSCqBNxqfvl6S5eJA4dXxyYCpDMzOLREQJGpXLenMtUxllZuS4nVfq2fGDF7zDOCQrUbPbx4rSSMusKAsvtIfDb",
      "needs_ocr": false
    },
    {
      "doc_id": "FRCL-2026-1285",
      "doc_type": "FRCL",
      "cat": "FORECLOSURE",
      "cat_label": "Foreclosure Posting",
      "sale_date": "05/05/2026",
      "file_date": "02/19/2026",
      "date_scraped": "2026-04-13",
      "batch_id": "B1",
      "batch_label": "Batch 1 \u2014 2026-04-13 02:58 AM",
      "grantor": "",
      "co_borrower": "",
      "amount": "",
      "mortgagee": "authorized to represent the Mortgagee by virtue of a",
      "legal_description": "in the attached Exhibit A. \u2014_! . . te 6. Mortgage Servicer Information. The Mortgage Servicer is authorized to represent the Mortgagee by virtue of a . * servicing agreement with the Mortgagee. Pursuant to the Servicing Agreement and Texas Property Code \u00a7 51.0025, the Mortgage Servicer is authorized to collect the debt and to administer any resulting foreclosure of the lien securing the Property referenced above. LOANCARE, LLC, as Mortgage Servicer, is representing the current mortgagee, whose address = is: \" , \"4 clo LOANCARE, LLC . S 3637 SENTARA WAY oO VIRGINIA BEACH, VA 23452 . wo N oO / . N \" . ~ oO) o / . Aad . N O Le Lu . 4 + iL , - FCTX_NTSS spt (11/17/2020)-S Ver-03 NTSS00000008233603 Page 1 of 3 10810 SILVERADO TRACE DR 00000008233603 HOUSTON, TX 77095 WY) THIS INSTRUMENT APPOINTS THE SUBSTITUTE TRUSTEE(S) IDENTIFIED TO SELL THE PROPERTY x DESCRIBED IN",
      "prop_address": "Not found",
      "prop_city": "",
      "prop_state": "TX",
      "prop_zip": "",
      "match_confidence": "none",
      "hcad_url": "",
      "clerk_url": "https://www.cclerk.hctx.net/applications/websearch/ViewECdocs.aspx?ID=bWXqGXasMeuE7YZXR3B2NdRpQgMQd0Nsa06X5vPrNVRh57zz7sHk4O3JxnwzRQIh0AbsF+lW1KIOi43s86sKO5yxinJ4VzIv8pzCOD7S/UDdNYsXMwxIsbSPiFVSZu0q",
      "needs_ocr": false
    },
    {
      "doc_id": "FRCL-2026-1286",
      "doc_type": "FRCL",
      "cat": "FORECLOSURE",
      "cat_label": "Foreclosure Posting",
      "sale_date": "05/05/2026",
      "file_date": "02/19/2026",
      "date_scraped": "2026-04-13",
      "batch_id": "B1",
      "batch_label": "Batch 1 \u2014 2026-04-13 02:58 AM",
      "grantor": "",
      "co_borrower": "",
      "amount": "",
      "mortgagee": "authorized to represent the Wloitgagee by virtue of a\nservicing agreement with the Mortgagee",
      "legal_description": "LOT FOURTEEN (14), IN BLOCK TWO (2), OF REMINGTON RANCH, SECTION TEN (10), A SUBDIVISION IN HARRIS oO COUNTY, TEXAS",
      "prop_address": "Not found",
      "prop_city": "",
      "prop_state": "TX",
      "prop_zip": "",
      "match_confidence": "none",
      "hcad_url": "",
      "clerk_url": "https://www.cclerk.hctx.net/applications/websearch/ViewECdocs.aspx?ID=bWXqGXasMeuE7YZXR3B2NdRpQgMQd0Nsa06X5vPrNVSKJKgULOL5PokyAnYHdedd0kpEE2D3JnejzaJur+zBzAPDpL9YaGtLL5Ru56Ry5O/Be1/7P3XSKZENwPDDSyIw",
      "needs_ocr": false
    },
    {
      "doc_id": "FRCL-2026-1287",
      "doc_type": "FRCL",
      "cat": "FORECLOSURE",
      "cat_label": "Foreclosure Posting",
      "sale_date": "05/05/2026",
      "file_date": "02/19/2026",
      "date_scraped": "2026-04-13",
      "batch_id": "B1",
      "batch_label": "Batch 1 \u2014 2026-04-13 02:58 AM",
      "grantor": "",
      "co_borrower": "",
      "amount": "$428,041.00",
      "mortgagee": "",
      "legal_description": "in the attached Exhibit A. e 6q@MMorage\\Seryiser Information. The Mortgage Servicer is authorized to represent the Mortgagee by virtue of a * DscrVicin@ arecment with the Mortgagee. Pursuant to the Servicing Agreement and Texas Property Code \u00a7 51.0025, the \u00bb \"Mortgage \"SePvicer is authorized to collect the debt and to administer any resulting foreclosure of the lien securing the \\y, Property\u00bb referenced above. MIDLAND MORTGAGE, A DIVISION OF MIDFIRST BANK, as Mortgage Servicer, is 2 _-\"@jpggPresenting the current mortgagee, whose address is: | \"4 ~ c/o MIDLAND MORTGAGE, A DIVISION OF MIDFIRST BANK . S 999 N.W. GRAND BLVD : os STE 110 wo OKLAHOMA CITY, OK 73118-6077 o A ~~ / a a ~ N . O Lu \u2014l iL FCTX_NTSS.rpt (11/17/2020)-S Ver-03 NTSS00000010729127 Page l of 3 2016 BRISTOL CLIFF LANE 00000010729127 PEARLAND, TX 77089 Y- THIS INSTRUMENT APPOINTS THE SUBSTITUTE TRUSTEE(S) IDENTIFIED TO SELL THE PROPERTY x DESCRIBED IN",
      "prop_address": "2016 BRISTOL CLIFF LANE",
      "prop_city": "PEARLAND",
      "prop_state": "TX",
      "prop_zip": "77089",
      "match_confidence": "high",
      "hcad_url": "",
      "clerk_url": "https://www.cclerk.hctx.net/applications/websearch/ViewECdocs.aspx?ID=bWXqGXasMeuE7YZXR3B2NdRpQgMQd0Nsa06X5vPrNVRv3GzDS5V1UE2ylIwv9yWM7RHa0EbeFfq3sNxRR0IJ8zLZCFwYIgrNQN/F7LU16AGCH40bGZzJAc3874VBJUIo",
      "needs_ocr": false
    },
    {
      "doc_id": "FRCL-2026-1235",
      "doc_type": "FRCL",
      "cat": "FORECLOSURE",
      "cat_label": "Foreclosure Posting",
      "sale_date": "05/05/2026",
      "file_date": "02/19/2026",
      "date_scraped": "2026-04-13",
      "batch_id": "B1",
      "batch_label": "Batch 1 \u2014 2026-04-13 02:58 AM",
      "grantor": "Tesia Rechette Harbour a single person",
      "co_borrower": "",
      "amount": "$219,942",
      "mortgagee": "",
      "legal_description": "Lot Five (5), In Block Two (2), Of Remmgton Creek Ranch Mayle in Harris County",
      "prop_address": "Not found",
      "prop_city": "",
      "prop_state": "TX",
      "prop_zip": "",
      "match_confidence": "none",
      "hcad_url": "",
      "clerk_url": "https://www.cclerk.hctx.net/applications/websearch/ViewECdocs.aspx?ID=bWXqGXasMeuE7YZXR3B2NUNXeLVZTKlhHSbKofnpRC4lb3MpvwtXif6Tce7x41E8KZC7Vwr3j1Bebapqs9OsdruilKonJf581GFVq1NM6cweWMgIvTA2jO5CM258D+bf",
      "needs_ocr": false
    },
    {
      "doc_id": "FRCL-2026-1236",
      "doc_type": "FRCL",
      "cat": "FORECLOSURE",
      "cat_label": "Foreclosure Posting",
      "sale_date": "05/05/2026",
      "file_date": "02/19/2026",
      "date_scraped": "2026-04-13",
      "batch_id": "B1",
      "batch_label": "Batch 1 \u2014 2026-04-13 02:58 AM",
      "grantor": "executed by TYLER CLARK",
      "co_borrower": "",
      "amount": "",
      "mortgagee": "",
      "legal_description": "t . SLE EXHIBIT \"A\" L- =_ ~",
      "prop_address": "9 KNIGHT RD",
      "prop_city": "HOUSTON",
      "prop_state": "TX",
      "prop_zip": "77045",
      "match_confidence": "high",
      "hcad_url": "",
      "clerk_url": "https://www.cclerk.hctx.net/applications/websearch/ViewECdocs.aspx?ID=bWXqGXasMeuE7YZXR3B2NXW7+UCmLW1nhGEPTIdxiNE9vMWaZYzrE2KDb8xT+VWbwEfdTaHaMvdCD6CSdJQpcUydaraKpg+0jRnnYtpYuppcgW156rUvIJGoTNBwB0Qs",
      "needs_ocr": false
    },
    {
      "doc_id": "FRCL-2026-1237",
      "doc_type": "FRCL",
      "cat": "FORECLOSURE",
      "cat_label": "Foreclosure Posting",
      "sale_date": "05/05/2026",
      "file_date": "02/19/2026",
      "date_scraped": "2026-04-13",
      "batch_id": "B1",
      "batch_label": "Batch 1 \u2014 2026-04-13 02:58 AM",
      "grantor": "",
      "co_borrower": "",
      "amount": "$206,196",
      "mortgagee": "",
      "legal_description": "",
      "prop_address": "Not found",
      "prop_city": "",
      "prop_state": "TX",
      "prop_zip": "",
      "match_confidence": "none",
      "hcad_url": "",
      "clerk_url": "https://www.cclerk.hctx.net/applications/websearch/ViewECdocs.aspx?ID=bWXqGXasMeuE7YZXR3B2NUNXeLVZTKlhHSbKofnpRC5oL8Iy7yC0KNHNk/+RJNpsrXkty0Z143NYLvqjA/uxWfwJgMpRktCw+9G288Ft+LdPx8pGPeKHXsAswuWJZfdI",
      "needs_ocr": false
    },
    {
      "doc_id": "FRCL-2026-1238",
      "doc_type": "FRCL",
      "cat": "FORECLOSURE",
      "cat_label": "Foreclosure Posting",
      "sale_date": "05/05/2026",
      "file_date": "02/19/2026",
      "date_scraped": "2026-04-13",
      "batch_id": "B1",
      "batch_label": "Batch 1 \u2014 2026-04-13 02:58 AM",
      "grantor": "",
      "co_borrower": "",
      "amount": "",
      "mortgagee": "",
      "legal_description": "",
      "prop_address": "Not found",
      "prop_city": "",
      "prop_state": "TX",
      "prop_zip": "",
      "match_confidence": "none",
      "hcad_url": "",
      "clerk_url": "https://www.cclerk.hctx.net/applications/websearch/ViewECdocs.aspx?ID=bWXqGXasMeuE7YZXR3B2NUNXeLVZTKlhHSbKofnpRC7tsWpKhb6AAEqd30WpqR3wMBHyLgRYZ39MBIMTZdJF15QzBA7aY5XLnrxk8856HuOwZJrlJu+mLV+ui9IfvrhF",
      "needs_ocr": false
    },
    {
      "doc_id": "FRCL-2026-1239",
      "doc_type": "FRCL",
      "cat": "FORECLOSURE",
      "cat_label": "Foreclosure Posting",
      "sale_date": "05/05/2026",
      "file_date": "02/19/2026",
      "date_scraped": "2026-04-13",
      "batch_id": "B1",
      "batch_label": "Batch 1 \u2014 2026-04-13 02:58 AM",
      "grantor": "",
      "co_borrower": "",
      "amount": "$5",
      "mortgagee": "",
      "legal_description": "Lot Six (6), n Block Srxty-Five (65), of Tmiber Lane, Section Seven (7), A Subdivision, m Harris County",
      "prop_address": "Not found",
      "prop_city": "",
      "prop_state": "TX",
      "prop_zip": "",
      "match_confidence": "none",
      "hcad_url": "",
      "clerk_url": "https://www.cclerk.hctx.net/applications/websearch/ViewECdocs.aspx?ID=bWXqGXasMeuE7YZXR3B2NUNXeLVZTKlhHSbKofnpRC7XoXDC7TDRzu7rMHeb08SSY/kUyFtzmWgMjZCYZT+YEyZKWoE2Kv3o4dJ0rEXKHpowb2omDCAFzskRQciV3EcF",
      "needs_ocr": false
    },
    {
      "doc_id": "FRCL-2026-1320",
      "doc_type": "FRCL",
      "cat": "FORECLOSURE",
      "cat_label": "Foreclosure Posting",
      "sale_date": "05/05/2026",
      "file_date": "02/19/2026",
      "date_scraped": "2026-04-13",
      "batch_id": "B1",
      "batch_label": "Batch 1 \u2014 2026-04-13 02:58 AM",
      "grantor": "",
      "co_borrower": "",
      "amount": "",
      "mortgagee": "",
      "legal_description": "9 . ' 91 009 of the Texas Property Code the property'wull-be sold mASIS WHERE TS condition wathout any express or amplied warranties . except as to the warranbes.of utle 1 anj, provided for under the-",
      "prop_address": "Not found",
      "prop_city": "",
      "prop_state": "TX",
      "prop_zip": "",
      "match_confidence": "none",
      "hcad_url": "",
      "clerk_url": "https://www.cclerk.hctx.net/applications/websearch/ViewECdocs.aspx?ID=bWXqGXasMeuE7YZXR3B2NSvzTel3b4phRC1xP2A+jyu6EA3cKF6SdoD12PhPoNYCrxv/7Ht47zXOwV3L4Q2X9LIMASQcSFe7DW1KqbbMZddMgrH2C+ui2ShH+wnZW1QQ",
      "needs_ocr": false
    },
    {
      "doc_id": "FRCL-2026-1321",
      "doc_type": "FRCL",
      "cat": "FORECLOSURE",
      "cat_label": "Foreclosure Posting",
      "sale_date": "05/05/2026",
      "file_date": "02/19/2026",
      "date_scraped": "2026-04-13",
      "batch_id": "B2",
      "batch_label": "Batch 2 \u2014 2026-04-13 12:25 PM",
      "grantor": "",
      "co_borrower": "",
      "amount": "$262",
      "mortgagee": "",
      "legal_description": "LOT SEVENTY ONE (71) BLOCK THIRTEEN (13) Yn . LAKEWOOD FOREST SECTION ONE (1) A SUBDIVISION IN HARRIS COUNTY",
      "prop_address": "Not found",
      "prop_city": "",
      "prop_state": "TX",
      "prop_zip": "",
      "match_confidence": "none",
      "hcad_url": "",
      "clerk_url": "https://www.cclerk.hctx.net/applications/websearch/ViewECdocs.aspx?ID=bWXqGXasMeuE7YZXR3B2NSvzTel3b4phRC1xP2A+jytpI03XXkltZn7IXPH4upf5L/luHLH1+sDYwj2RswugC/YdL/r/tfI5HYZsyCXptDsH/Ifkm3tpRB/TGSlZmUiX",
      "needs_ocr": false
    },
    {
      "doc_id": "FRCL-2026-1322",
      "doc_type": "FRCL",
      "cat": "FORECLOSURE",
      "cat_label": "Foreclosure Posting",
      "sale_date": "05/05/2026",
      "file_date": "02/19/2026",
      "date_scraped": "2026-04-13",
      "batch_id": "B2",
      "batch_label": "Batch 2 \u2014 2026-04-13 12:25 PM",
      "grantor": "",
      "co_borrower": "",
      "amount": "$52",
      "mortgagee": "",
      "legal_description": "LOT EIGHTLEN (18} IN BLOCK ONE (1) OF Yn VERDE FOREST SECTION ONE (1) A SUBDIVISION IN HARRIS COUNTS. TEXAS ACCORDING TO THE MAP OR pa PLAT THEREOF RECORDED IN VOLUME 168 PAGE 142 OF THE MAP RECORDS OF HARRIS COUNTY",
      "prop_address": "Not found",
      "prop_city": "",
      "prop_state": "TX",
      "prop_zip": "",
      "match_confidence": "none",
      "hcad_url": "",
      "clerk_url": "https://www.cclerk.hctx.net/applications/websearch/ViewECdocs.aspx?ID=bWXqGXasMeuE7YZXR3B2NSvzTel3b4phRC1xP2A+jytsNYkOUTmrw5mKqdGPaVg/peIOTuhTrBTsB6RIWDsFC7TowQml0jhpfZV4SX459dwuTt1gZlyYizopeQmijN75",
      "needs_ocr": false
    },
    {
      "doc_id": "FRCL-2026-1323",
      "doc_type": "FRCL",
      "cat": "FORECLOSURE",
      "cat_label": "Foreclosure Posting",
      "sale_date": "05/05/2026",
      "file_date": "02/19/2026",
      "date_scraped": "2026-04-13",
      "batch_id": "B2",
      "batch_label": "Batch 2 \u2014 2026-04-13 12:25 PM",
      "grantor": "",
      "co_borrower": "",
      "amount": "$142",
      "mortgagee": "",
      "legal_description": "",
      "prop_address": "Not found",
      "prop_city": "",
      "prop_state": "TX",
      "prop_zip": "",
      "match_confidence": "none",
      "hcad_url": "",
      "clerk_url": "https://www.cclerk.hctx.net/applications/websearch/ViewECdocs.aspx?ID=bWXqGXasMeuE7YZXR3B2NSvzTel3b4phRC1xP2A+jyvCHvFP8BqItgz199f82omj1ci4j1TOaqwyP3ULpUmNFTyBVlx170Jm3ooSnn3iK9tsEoDX+6dfJqHq0IUHdd2o",
      "needs_ocr": false
    },
    {
      "doc_id": "FRCL-2026-1324",
      "doc_type": "FRCL",
      "cat": "FORECLOSURE",
      "cat_label": "Foreclosure Posting",
      "sale_date": "05/05/2026",
      "file_date": "02/19/2026",
      "date_scraped": "2026-04-13",
      "batch_id": "B2",
      "batch_label": "Batch 2 \u2014 2026-04-13 12:25 PM",
      "grantor": "",
      "co_borrower": "",
      "amount": "$263,934",
      "mortgagee": "",
      "legal_description": "oO LOT NINE (9), IN BLOCK ONE (ij, OF CYPRESSWOOD POINT SEC 11, A SUBDIVISION IN HARRIS > COUNTY, TEXAS",
      "prop_address": "Not found",
      "prop_city": "",
      "prop_state": "TX",
      "prop_zip": "",
      "match_confidence": "none",
      "hcad_url": "",
      "clerk_url": "https://www.cclerk.hctx.net/applications/websearch/ViewECdocs.aspx?ID=bWXqGXasMeuE7YZXR3B2NdRpQgMQd0Nsa06X5vPrNVSgitHUUshi+lfgW0o07PCrVjUEBEavFfUDFQKOmrEuihMMRwoakWbI1iEbrOsoJhcNgtt/nCWeajw/TmwhgreL",
      "needs_ocr": false
    },
    {
      "doc_id": "FRCL-2026-1325",
      "doc_type": "FRCL",
      "cat": "FORECLOSURE",
      "cat_label": "Foreclosure Posting",
      "sale_date": "05/05/2026",
      "file_date": "02/19/2026",
      "date_scraped": "2026-04-13",
      "batch_id": "B2",
      "batch_label": "Batch 2 \u2014 2026-04-13 12:25 PM",
      "grantor": "KENNETH STUBBLEFIELD",
      "co_borrower": "",
      "amount": "$382,000",
      "mortgagee": "",
      "legal_description": "G LOT TWENTY-ONE (21), IN BLOCK THES), GF BRADBURY FOREST SEC TEN (10), A SUBDIVISION ec IN HARRIS COUNTY",
      "prop_address": "Not found",
      "prop_city": "",
      "prop_state": "TX",
      "prop_zip": "",
      "match_confidence": "none",
      "hcad_url": "",
      "clerk_url": "https://www.cclerk.hctx.net/applications/websearch/ViewECdocs.aspx?ID=bWXqGXasMeuE7YZXR3B2NdRpQgMQd0Nsa06X5vPrNVQMy1OKCavKNAoomQU7FXToGsb9CAbiq59boBcupmGFIioRXmDtWLUwfAaefuVnASeaESm/M3R1gQc6CwaMq5bq",
      "needs_ocr": false
    },
    {
      "doc_id": "FRCL-2026-1326",
      "doc_type": "FRCL",
      "cat": "FORECLOSURE",
      "cat_label": "Foreclosure Posting",
      "sale_date": "05/05/2026",
      "file_date": "02/19/2026",
      "date_scraped": "2026-04-13",
      "batch_id": "B2",
      "batch_label": "Batch 2 \u2014 2026-04-13 12:25 PM",
      "grantor": "Lekart Davis, a single man",
      "co_borrower": "",
      "amount": "$461,388",
      "mortgagee": "",
      "legal_description": "",
      "prop_address": "Not found",
      "prop_city": "",
      "prop_state": "TX",
      "prop_zip": "",
      "match_confidence": "none",
      "hcad_url": "",
      "clerk_url": "https://www.cclerk.hctx.net/applications/websearch/ViewECdocs.aspx?ID=bWXqGXasMeuE7YZXR3B2NdRpQgMQd0Nsa06X5vPrNVTvyZJwRdw5yCdu9S8cluJl4/xO2exCmEFN1rfHmK3I7aZoePM6z1lKihY3NzgFYxskQw3eu4mE3kC3uwLIn5ow",
      "needs_ocr": false
    },
    {
      "doc_id": "FRCL-2026-1342",
      "doc_type": "FRCL",
      "cat": "FORECLOSURE",
      "cat_label": "Foreclosure Posting",
      "sale_date": "05/05/2026",
      "file_date": "02/20/2026",
      "date_scraped": "2026-04-13",
      "batch_id": "B2",
      "batch_label": "Batch 2 \u2014 2026-04-13 12:25 PM",
      "grantor": "",
      "co_borrower": "",
      "amount": "",
      "mortgagee": "",
      "legal_description": "Lot Twenty-One(21), If Bleek Tweniy-Five(25), of ARLINGTON HEIGHTS, SECTION TWO . = (2), a'subdivision in Harris County",
      "prop_address": "Not found",
      "prop_city": "",
      "prop_state": "TX",
      "prop_zip": "",
      "match_confidence": "none",
      "hcad_url": "",
      "clerk_url": "https://www.cclerk.hctx.net/applications/websearch/ViewECdocs.aspx?ID=bWXqGXasMeuE7YZXR3B2NUNXeLVZTKlhHSbKofnpRC4z+qujmNLxkmWP8p25QW9OQW36n122Xoid1j7aZOLKZFQHQ9k/5H5xzv3bo65B2WphIeOjPqGp2IizLSwoBGdh",
      "needs_ocr": false
    },
    {
      "doc_id": "FRCL-2026-1347",
      "doc_type": "FRCL",
      "cat": "FORECLOSURE",
      "cat_label": "Foreclosure Posting",
      "sale_date": "05/05/2026",
      "file_date": "02/24/2026",
      "date_scraped": "2026-04-13",
      "batch_id": "B2",
      "batch_label": "Batch 2 \u2014 2026-04-13 12:25 PM",
      "grantor": "",
      "co_borrower": "",
      "amount": "",
      "mortgagee": "",
      "legal_description": "",
      "prop_address": "Not found",
      "prop_city": "",
      "prop_state": "TX",
      "prop_zip": "",
      "match_confidence": "none",
      "hcad_url": "",
      "clerk_url": "https://www.cclerk.hctx.net/applications/websearch/ViewECdocs.aspx?ID=bWXqGXasMeuE7YZXR3B2NSvzTel3b4phRC1xP2A+jytliF/VgMvUFNTKxdXOO/UOtmBwqHzl4DNNmfq51yE1S7Hfg+4Csr6fN89evNf4zCyoTt4Pu98fL0XqiTVwRDd8",
      "needs_ocr": false
    },
    {
      "doc_id": "FRCL-2026-1355",
      "doc_type": "FRCL",
      "cat": "FORECLOSURE",
      "cat_label": "Foreclosure Posting",
      "sale_date": "05/05/2026",
      "file_date": "02/24/2026",
      "date_scraped": "2026-04-13",
      "batch_id": "B2",
      "batch_label": "Batch 2 \u2014 2026-04-13 12:25 PM",
      "grantor": "",
      "co_borrower": "",
      "amount": "",
      "mortgagee": "",
      "legal_description": "",
      "prop_address": "Not found",
      "prop_city": "",
      "prop_state": "TX",
      "prop_zip": "",
      "match_confidence": "none",
      "hcad_url": "",
      "clerk_url": "https://www.cclerk.hctx.net/applications/websearch/ViewECdocs.aspx?ID=bWXqGXasMeuE7YZXR3B2NdRpQgMQd0Nsa06X5vPrNVQKeKffFBZ+sPuR9ZzmsFHNa084QyGEBrccB2O8AREUlS1nJclSxj22ZSFKFG8k0koa9UI+c+OAFIExYWv4xiBE",
      "needs_ocr": false
    },
    {
      "doc_id": "FRCL-2026-1356",
      "doc_type": "FRCL",
      "cat": "FORECLOSURE",
      "cat_label": "Foreclosure Posting",
      "sale_date": "05/05/2026",
      "file_date": "02/24/2026",
      "date_scraped": "2026-04-13",
      "batch_id": "B2",
      "batch_label": "Batch 2 \u2014 2026-04-13 12:25 PM",
      "grantor": "",
      "co_borrower": "",
      "amount": "",
      "mortgagee": "",
      "legal_description": "",
      "prop_address": "Not found",
      "prop_city": "",
      "prop_state": "TX",
      "prop_zip": "",
      "match_confidence": "none",
      "hcad_url": "",
      "clerk_url": "https://www.cclerk.hctx.net/applications/websearch/ViewECdocs.aspx?ID=bWXqGXasMeuE7YZXR3B2NdRpQgMQd0Nsa06X5vPrNVTyvAMGT5SFAgN4XdAbIhXb7yBa4SkmE9N9HOVliVaanoCaHw+CSyLnfpVQ75V9jdKvUWF+jnJAGAgb4pMqE/D7",
      "needs_ocr": false
    },
    {
      "doc_id": "FRCL-2026-1363",
      "doc_type": "FRCL",
      "cat": "FORECLOSURE",
      "cat_label": "Foreclosure Posting",
      "sale_date": "05/05/2026",
      "file_date": "02/26/2026",
      "date_scraped": "2026-04-13",
      "batch_id": "B2",
      "batch_label": "Batch 2 \u2014 2026-04-13 12:25 PM",
      "grantor": "",
      "co_borrower": "",
      "amount": "",
      "mortgagee": "authorized to represent the Mortgagee by virtue of a\n\na servicing agreementmayith the MOrtgagee",
      "legal_description": "",
      "prop_address": "Not found",
      "prop_city": "",
      "prop_state": "TX",
      "prop_zip": "",
      "match_confidence": "none",
      "hcad_url": "",
      "clerk_url": "https://www.cclerk.hctx.net/applications/websearch/ViewECdocs.aspx?ID=bWXqGXasMeuE7YZXR3B2NdRpQgMQd0Nsa06X5vPrNVQoyG3lWi7l0bWrgX5arVWoqh2Lyi/NnhpkAZ1OMQrhiWPYIYdNVifjApf5OsmlFazyVBAg6I1ye+qsm5z9+0Se",
      "needs_ocr": false
    },
    {
      "doc_id": "FRCL-2026-1364",
      "doc_type": "FRCL",
      "cat": "FORECLOSURE",
      "cat_label": "Foreclosure Posting",
      "sale_date": "05/05/2026",
      "file_date": "02/26/2026",
      "date_scraped": "2026-04-13",
      "batch_id": "B2",
      "batch_label": "Batch 2 \u2014 2026-04-13 12:25 PM",
      "grantor": "",
      "co_borrower": "",
      "amount": "$268,055.00",
      "mortgagee": "authorized to represent the Mortgagee by virtue of a\n\nac servicing agreement with the Mortgagee",
      "legal_description": "",
      "prop_address": "28702 IDLELOCH DR",
      "prop_city": "Zz HUFFMAN",
      "prop_state": "TX",
      "prop_zip": "77336",
      "match_confidence": "high",
      "hcad_url": "",
      "clerk_url": "https://www.cclerk.hctx.net/applications/websearch/ViewECdocs.aspx?ID=bWXqGXasMeuE7YZXR3B2NdRpQgMQd0Nsa06X5vPrNVSYnd7nWffzSzFYYiWWI5YofMXy5BKotdaG/sm4+BTq4DWSmWVJGlQAsLITRpua1AtO0lPXuTz2T7byydaXrX97",
      "needs_ocr": false
    },
    {
      "doc_id": "FRCL-2026-1365",
      "doc_type": "FRCL",
      "cat": "FORECLOSURE",
      "cat_label": "Foreclosure Posting",
      "sale_date": "05/05/2026",
      "file_date": "02/26/2026",
      "date_scraped": "2026-04-13",
      "batch_id": "B2",
      "batch_label": "Batch 2 \u2014 2026-04-13 12:25 PM",
      "grantor": "",
      "co_borrower": "",
      "amount": "$122,000.00",
      "mortgagee": "authorized to represent the Mortgagee by virtue of a\nservicing agreement with the Mortgagee",
      "legal_description": "LOT ONE (1), IN BLOCK ONE (1), OF GLEN ABBEY SECTION' TWO (2) A SUBDIVISION IN HARRIS COUNTY",
      "prop_address": "9404 KNIGHT ROAD",
      "prop_city": "HOUSTON",
      "prop_state": "TX",
      "prop_zip": "77045",
      "match_confidence": "high",
      "hcad_url": "",
      "clerk_url": "https://www.cclerk.hctx.net/applications/websearch/ViewECdocs.aspx?ID=bWXqGXasMeuE7YZXR3B2NdRpQgMQd0Nsa06X5vPrNVRmqkkWrbuyxJjQuWlBGUraGl4wk/WDgaWOWWAg+9CogyEwp/5ztRUsmfOHVktfThQc2iJGon2vDJXpQmQq8/I+",
      "needs_ocr": false
    },
    {
      "doc_id": "FRCL-2026-1366",
      "doc_type": "FRCL",
      "cat": "FORECLOSURE",
      "cat_label": "Foreclosure Posting",
      "sale_date": "05/05/2026",
      "file_date": "02/26/2026",
      "date_scraped": "2026-04-13",
      "batch_id": "B2",
      "batch_label": "Batch 2 \u2014 2026-04-13 12:25 PM",
      "grantor": "",
      "co_borrower": "",
      "amount": "$78,996.00",
      "mortgagee": "",
      "legal_description": "LOT THREE (3) BLOCK FIFTY-SEVEN (57), OF FOREST OAKS ADDITION, A SUBDIVISION IN HARRIS COUNTY",
      "prop_address": "Not found",
      "prop_city": "",
      "prop_state": "TX",
      "prop_zip": "",
      "match_confidence": "none",
      "hcad_url": "",
      "clerk_url": "https://www.cclerk.hctx.net/applications/websearch/ViewECdocs.aspx?ID=bWXqGXasMeuE7YZXR3B2NdRpQgMQd0Nsa06X5vPrNVQTuhyfPKUXMwnkk3HgRaRBrjKd1UDpHyH91EoD+5766wL+Y6ACkL7oP8i2HylAdXE0Pd2fKRL8U8QE6x+aBUvh",
      "needs_ocr": false
    },
    {
      "doc_id": "FRCL-2026-1367",
      "doc_type": "FRCL",
      "cat": "FORECLOSURE",
      "cat_label": "Foreclosure Posting",
      "sale_date": "05/05/2026",
      "file_date": "02/26/2026",
      "date_scraped": "2026-04-13",
      "batch_id": "B2",
      "batch_label": "Batch 2 \u2014 2026-04-13 12:25 PM",
      "grantor": "",
      "co_borrower": "",
      "amount": "",
      "mortgagee": "",
      "legal_description": "",
      "prop_address": "Not found",
      "prop_city": "",
      "prop_state": "TX",
      "prop_zip": "",
      "match_confidence": "none",
      "hcad_url": "",
      "clerk_url": "https://www.cclerk.hctx.net/applications/websearch/ViewECdocs.aspx?ID=bWXqGXasMeuE7YZXR3B2NdRpQgMQd0Nsa06X5vPrNVSOGySG7hvuCGLQrtFoaUss3fAECK6hER5sF9boELdRjSrZi5815TqARWcKvRPybXrZJM08+HiQ++0jUJ0lOU7p",
      "needs_ocr": false
    },
    {
      "doc_id": "FRCL-2026-1368",
      "doc_type": "FRCL",
      "cat": "FORECLOSURE",
      "cat_label": "Foreclosure Posting",
      "sale_date": "05/05/2026",
      "file_date": "02/26/2026",
      "date_scraped": "2026-04-13",
      "batch_id": "B2",
      "batch_label": "Batch 2 \u2014 2026-04-13 12:25 PM",
      "grantor": "",
      "co_borrower": "",
      "amount": "$332,926.00",
      "mortgagee": "",
      "legal_description": "",
      "prop_address": "2805 ANITA STREET",
      "prop_city": "z HOUSTON",
      "prop_state": "TX",
      "prop_zip": "77004",
      "match_confidence": "high",
      "hcad_url": "",
      "clerk_url": "https://www.cclerk.hctx.net/applications/websearch/ViewECdocs.aspx?ID=bWXqGXasMeuE7YZXR3B2NdRpQgMQd0Nsa06X5vPrNVRhgmDb7fzpmfwAExd67wTWuZg4JXRf3xJrIPIbkbI6So0IrPPHXNCBHpyPs1Q0DTSjCT1DWSYOgIkSAjjuEJ78",
      "needs_ocr": false
    },
    {
      "doc_id": "FRCL-2026-1369",
      "doc_type": "FRCL",
      "cat": "FORECLOSURE",
      "cat_label": "Foreclosure Posting",
      "sale_date": "05/05/2026",
      "file_date": "02/26/2026",
      "date_scraped": "2026-04-13",
      "batch_id": "B2",
      "batch_label": "Batch 2 \u2014 2026-04-13 12:25 PM",
      "grantor": "DEBORAH GAY ROSS",
      "co_borrower": "",
      "amount": "",
      "mortgagee": "",
      "legal_description": "",
      "prop_address": "3 HOUST",
      "prop_city": "ON",
      "prop_state": "TX",
      "prop_zip": "77069",
      "match_confidence": "high",
      "hcad_url": "",
      "clerk_url": "https://www.cclerk.hctx.net/applications/websearch/ViewECdocs.aspx?ID=bWXqGXasMeuE7YZXR3B2NdRpQgMQd0Nsa06X5vPrNVQUB7O8fVw9K1P/1GMbtfiGPNw/VxNDe+vkPNEmGBSRQOZVgKz+Z6q9OewsqAcbujXu0wFGx3wfZbDonTbSxlCp",
      "needs_ocr": false
    },
    {
      "doc_id": "FRCL-2026-1370",
      "doc_type": "FRCL",
      "cat": "FORECLOSURE",
      "cat_label": "Foreclosure Posting",
      "sale_date": "05/05/2026",
      "file_date": "02/26/2026",
      "date_scraped": "2026-04-13",
      "batch_id": "B2",
      "batch_label": "Batch 2 \u2014 2026-04-13 12:25 PM",
      "grantor": "",
      "co_borrower": "",
      "amount": "$66,411.00",
      "mortgagee": "authorized to represent the Mortgagee by virtue of a\nservicing agreement with the Mortgagee",
      "legal_description": "",
      "prop_address": "Not found",
      "prop_city": "",
      "prop_state": "TX",
      "prop_zip": "",
      "match_confidence": "none",
      "hcad_url": "",
      "clerk_url": "https://www.cclerk.hctx.net/applications/websearch/ViewECdocs.aspx?ID=bWXqGXasMeuE7YZXR3B2NdRpQgMQd0Nsa06X5vPrNVSGal0eihjt0uHnZCP55d8YEtledvcT8XXW2lCqfCInl4k8KhvtS1Cv72TFkMVPBN1w/ntpzwKYFJgPWgABF5ww",
      "needs_ocr": false
    },
    {
      "doc_id": "FRCL-2026-1371",
      "doc_type": "FRCL",
      "cat": "FORECLOSURE",
      "cat_label": "Foreclosure Posting",
      "sale_date": "05/05/2026",
      "file_date": "02/26/2026",
      "date_scraped": "2026-04-13",
      "batch_id": "B2",
      "batch_label": "Batch 2 \u2014 2026-04-13 12:25 PM",
      "grantor": "RAMIRO CAMPOS SINGLE",
      "co_borrower": "",
      "amount": "",
      "mortgagee": "authorized to collect the debt and to administer any resulting foreclosure of the lien securing the\nProperty referenced above",
      "legal_description": "",
      "prop_address": "Not found",
      "prop_city": "",
      "prop_state": "TX",
      "prop_zip": "",
      "match_confidence": "none",
      "hcad_url": "",
      "clerk_url": "https://www.cclerk.hctx.net/applications/websearch/ViewECdocs.aspx?ID=bWXqGXasMeuE7YZXR3B2NdRpQgMQd0Nsa06X5vPrNVT5bIi5n3xM3lvKpWWCC5QTtnf10/ongq7fDQU4G+Nr95JDG9o6vBzWBFYmED5C5nK4xfca+Ih506duds5rB/ru",
      "needs_ocr": false
    },
    {
      "doc_id": "FRCL-2026-1372",
      "doc_type": "FRCL",
      "cat": "FORECLOSURE",
      "cat_label": "Foreclosure Posting",
      "sale_date": "05/05/2026",
      "file_date": "02/26/2026",
      "date_scraped": "2026-04-13",
      "batch_id": "B2",
      "batch_label": "Batch 2 \u2014 2026-04-13 12:25 PM",
      "grantor": "",
      "co_borrower": "",
      "amount": "$94,801.00",
      "mortgagee": "authorized to represent the Mortgagee by virtue of a\nservicing agreement with the Mortgagee",
      "legal_description": "",
      "prop_address": "2535 TINECHESTER DRIVE",
      "prop_city": "a KINGWOOD",
      "prop_state": "TX",
      "prop_zip": "77339",
      "match_confidence": "high",
      "hcad_url": "",
      "clerk_url": "https://www.cclerk.hctx.net/applications/websearch/ViewECdocs.aspx?ID=bWXqGXasMeuE7YZXR3B2NdRpQgMQd0Nsa06X5vPrNVR628pnjinjffBuabnvI6/Kv0FCEPl/pwbzS8DyUac8fdsQDn4fTKCNx6E3W48JwL/gG08xrAKkyWoqOnm3/Mb5",
      "needs_ocr": false
    },
    {
      "doc_id": "FRCL-2026-1386",
      "doc_type": "FRCL",
      "cat": "FORECLOSURE",
      "cat_label": "Foreclosure Posting",
      "sale_date": "05/05/2026",
      "file_date": "02/26/2026",
      "date_scraped": "2026-04-13",
      "batch_id": "B2",
      "batch_label": "Batch 2 \u2014 2026-04-13 12:25 PM",
      "grantor": "",
      "co_borrower": "",
      "amount": "",
      "mortgagee": "",
      "legal_description": "- DESIGNATED BY THE COUNTY COMMISSIONERS OFFICE OR IN THE AREA DESIGNATED BY THE COMMISSIONER'S COURT, < -| PURSUANT TO SECTION 51.002 OF THE TEXAS PROPERTY CODE. 9 Legal Description: LOT 8, IN BLOCK 36, OF BEAR CREEK VILLAGE, SECTION 3 A SUBDIVISION IN HARRIS COUNTY",
      "prop_address": "Not found",
      "prop_city": "",
      "prop_state": "TX",
      "prop_zip": "",
      "match_confidence": "none",
      "hcad_url": "",
      "clerk_url": "https://www.cclerk.hctx.net/applications/websearch/ViewECdocs.aspx?ID=bWXqGXasMeuE7YZXR3B2NSvzTel3b4phRC1xP2A+jysPJgs6rcWy4nnDlDiHSUWJ2O2zMzHjXUfwgUXMfVzeIXaU6TqV57axw1Kn1wJC+fokxAWGf8dfbkwk6tjWz3+h",
      "needs_ocr": false
    },
    {
      "doc_id": "FRCL-2026-1387",
      "doc_type": "FRCL",
      "cat": "FORECLOSURE",
      "cat_label": "Foreclosure Posting",
      "sale_date": "05/05/2026",
      "file_date": "02/26/2026",
      "date_scraped": "2026-04-13",
      "batch_id": "B2",
      "batch_label": "Batch 2 \u2014 2026-04-13 12:25 PM",
      "grantor": "",
      "co_borrower": "",
      "amount": "",
      "mortgagee": "",
      "legal_description": "\u2014! DESIGNATED BY THE COUNTY COMMISSIONERS OFFICE OR IN THE AREA DESIGNATED BY THE COMMISSIONER'S COURT, > PURSUANT TO SECTION 51.002 OF THE TEXAS PROPERTY CODE. Zz g, (egal Description: LOT 1, IN BLOCK 1, OF AMOS STREET LANDING, A SUBDIVISION IN HARRIS COUNTY",
      "prop_address": "Not found",
      "prop_city": "",
      "prop_state": "TX",
      "prop_zip": "",
      "match_confidence": "none",
      "hcad_url": "",
      "clerk_url": "https://www.cclerk.hctx.net/applications/websearch/ViewECdocs.aspx?ID=bWXqGXasMeuE7YZXR3B2NSvzTel3b4phRC1xP2A+jyuLgtscVzCAJQlwhXD/YS08J6OjSEOhdPXkZsg/janN2cQUq5XKUYnBO00sGUmZ/kQQKfjRNjQNnWWBN6lWFypJ",
      "needs_ocr": false
    },
    {
      "doc_id": "FRCL-2026-1388",
      "doc_type": "FRCL",
      "cat": "FORECLOSURE",
      "cat_label": "Foreclosure Posting",
      "sale_date": "05/05/2026",
      "file_date": "02/26/2026",
      "date_scraped": "2026-04-13",
      "batch_id": "B2",
      "batch_label": "Batch 2 \u2014 2026-04-13 12:25 PM",
      "grantor": "",
      "co_borrower": "",
      "amount": "",
      "mortgagee": "",
      "legal_description": "ec DESIGNATED BY THE COUNTY COMMISSIONERS OFFI ORAN THE AREA DESIGNATED BY THE COMMISSIONER'S COURT, Zz PURSUANT TO SECTION 51.002 OF THE TEXAS PROPERTY CODE. _) : - / : . : << 9 Legal Description: LOT THIRTY-FOUR (34), IN BLOCK \"Kaa MEADOW, SECTION TWO (2), AN ADDITION IN HARRIS COUNTY",
      "prop_address": "Not found",
      "prop_city": "",
      "prop_state": "TX",
      "prop_zip": "",
      "match_confidence": "none",
      "hcad_url": "",
      "clerk_url": "https://www.cclerk.hctx.net/applications/websearch/ViewECdocs.aspx?ID=bWXqGXasMeuE7YZXR3B2NSvzTel3b4phRC1xP2A+jyvWSe5AsOP32/3dNnuiqSbMxPp+tWRprwIS5i0nCvYhtb6EqKx7OQEBuKfvxExYlXpBUSP+X9I1Ldt/nRjuK5yo",
      "needs_ocr": false
    },
    {
      "doc_id": "FRCL-2026-1361",
      "doc_type": "FRCL",
      "cat": "FORECLOSURE",
      "cat_label": "Foreclosure Posting",
      "sale_date": "05/05/2026",
      "file_date": "02/26/2026",
      "date_scraped": "2026-04-13",
      "batch_id": "B2",
      "batch_label": "Batch 2 \u2014 2026-04-13 12:25 PM",
      "grantor": "",
      "co_borrower": "",
      "amount": "",
      "mortgagee": "",
      "legal_description": "q THE PROPERTY LOCATED IN HARRIS COUNTY, TEXAS, INCLUDING Q PERSONAL PROPERTY, IF ANY, AS DESCRIBED IN",
      "prop_address": "Not found",
      "prop_city": "",
      "prop_state": "TX",
      "prop_zip": "",
      "match_confidence": "none",
      "hcad_url": "",
      "clerk_url": "https://www.cclerk.hctx.net/applications/websearch/ViewECdocs.aspx?ID=bWXqGXasMeuE7YZXR3B2NS3bRzpsleMPc8VGgBZ/oyF5KOruNEbfhNMmYcfXABxkrhWwhZhIMyaMSKn2YkYKIDO4pVq9BDmfvRx8YhwW2ZNVXhAcQPCVOGRx7sE6DPpI",
      "needs_ocr": false
    },
    {
      "doc_id": "FRCL-2026-1409",
      "doc_type": "FRCL",
      "cat": "FORECLOSURE",
      "cat_label": "Foreclosure Posting",
      "sale_date": "05/05/2026",
      "file_date": "02/26/2026",
      "date_scraped": "2026-04-13",
      "batch_id": "B2",
      "batch_label": "Batch 2 \u2014 2026-04-13 12:25 PM",
      "grantor": "",
      "co_borrower": "",
      "amount": "$286,250.00",
      "mortgagee": "the mortgagee",
      "legal_description": "ac < Lot 362 Block 11, of Villow Forggt Subdivision, Section Two, a subdivision in v, Harris County",
      "prop_address": "22510 RED PINE DR",
      "prop_city": "TOMBALL",
      "prop_state": "TX",
      "prop_zip": "77375",
      "match_confidence": "high",
      "hcad_url": "",
      "clerk_url": "https://www.cclerk.hctx.net/applications/websearch/ViewECdocs.aspx?ID=bWXqGXasMeuE7YZXR3B2NUNXeLVZTKlhHSbKofnpRC7rccPJJgY1C+q80UDUPKM5nq49pKAIz/YKlUdaaYrFKX3913D2G9X3e6bYLTJL2kj90dLwA2y/QYEilm8zlJkz",
      "needs_ocr": false
    },
    {
      "doc_id": "FRCL-2026-1410",
      "doc_type": "FRCL",
      "cat": "FORECLOSURE",
      "cat_label": "Foreclosure Posting",
      "sale_date": "05/05/2026",
      "file_date": "02/26/2026",
      "date_scraped": "2026-04-13",
      "batch_id": "B2",
      "batch_label": "Batch 2 \u2014 2026-04-13 12:25 PM",
      "grantor": "MARGARET D JOHNSON",
      "co_borrower": "",
      "amount": "$224,950.00",
      "mortgagee": "",
      "legal_description": "ac < Lot Ten (10), Block Org (1) of Lake good Grove, Section Ten (10), an addition ~ in Harris County",
      "prop_address": "8950 Cypress Waters Blvd",
      "prop_city": "Coppell",
      "prop_state": "TX",
      "prop_zip": "75019",
      "match_confidence": "high",
      "hcad_url": "",
      "clerk_url": "https://www.cclerk.hctx.net/applications/websearch/ViewECdocs.aspx?ID=bWXqGXasMeuE7YZXR3B2NUNXeLVZTKlhHSbKofnpRC7qAxDXPz5MYrjZHtCEMaWAytRu5Dr4pG1YcJloa0VSe4ebGhZgX6uP2lGr4NmAbcIDdKDcKvNmcj5dzXtj6oGQ",
      "needs_ocr": false
    },
    {
      "doc_id": "FRCL-2026-1411",
      "doc_type": "FRCL",
      "cat": "FORECLOSURE",
      "cat_label": "Foreclosure Posting",
      "sale_date": "05/05/2026",
      "file_date": "02/26/2026",
      "date_scraped": "2026-04-13",
      "batch_id": "B2",
      "batch_label": "Batch 2 \u2014 2026-04-13 12:25 PM",
      "grantor": "K INVESTMENTS LLC",
      "co_borrower": "",
      "amount": "$136,500.00",
      "mortgagee": "the mortgagee",
      "legal_description": "as follows: a ~ < LOT 103 AND LOT 104, IN BLOCK 3, OF YORKDALE ADDITION, v, SECTION ONE, A SUBDIVISION IN HARRIS COUNTY",
      "prop_address": "2635 CARMEL ST",
      "prop_city": "HOUSTON",
      "prop_state": "TX",
      "prop_zip": "77091",
      "match_confidence": "high",
      "hcad_url": "",
      "clerk_url": "https://www.cclerk.hctx.net/applications/websearch/ViewECdocs.aspx?ID=bWXqGXasMeuE7YZXR3B2NUNXeLVZTKlhHSbKofnpRC64BxgCNduROAAGimM/8eQvQarV7a3W9y48wUcT1k5PX489lz+CcSaLI1sNBtCwbbJ5gICVg18RywJ//xlFZm3t",
      "needs_ocr": false
    },
    {
      "doc_id": "FRCL-2026-1412",
      "doc_type": "FRCL",
      "cat": "FORECLOSURE",
      "cat_label": "Foreclosure Posting",
      "sale_date": "05/05/2026",
      "file_date": "02/26/2026",
      "date_scraped": "2026-04-13",
      "batch_id": "B2",
      "batch_label": "Batch 2 \u2014 2026-04-13 12:25 PM",
      "grantor": "",
      "co_borrower": "",
      "amount": "$127,645.00",
      "mortgagee": "the mortgagee",
      "legal_description": "as follows: ac < LOT TWO (2) , IN BLOCK FOUR (4), OF SHADY HILL VILLA, PHASE ~ ONE, AN ADDITION IN HARRIS COUNTY",
      "prop_address": "4717 INDIAN TRL",
      "prop_city": "BAYTOWN",
      "prop_state": "TX",
      "prop_zip": "77521",
      "match_confidence": "high",
      "hcad_url": "",
      "clerk_url": "https://www.cclerk.hctx.net/applications/websearch/ViewECdocs.aspx?ID=bWXqGXasMeuE7YZXR3B2NUNXeLVZTKlhHSbKofnpRC6yg0IodfFy5qu7kHhe4r7xnSioCmDd+M13HFelPC027yW1v3Ocvw+XMrzSew2cC1wl0vTnykxuZOPV/bdqt9Rb",
      "needs_ocr": false
    },
    {
      "doc_id": "FRCL-2026-1413",
      "doc_type": "FRCL",
      "cat": "FORECLOSURE",
      "cat_label": "Foreclosure Posting",
      "sale_date": "05/05/2026",
      "file_date": "02/26/2026",
      "date_scraped": "2026-04-13",
      "batch_id": "B2",
      "batch_label": "Batch 2 \u2014 2026-04-13 12:25 PM",
      "grantor": "AND",
      "co_borrower": "",
      "amount": "$000",
      "mortgagee": "the mortgagee",
      "legal_description": "as follows: ac < LOT TWO HUNDRED NINETY-NINE (299), IN BLOCK THREE (3), OF . v, CHATEAU FOREST, SECTION FOUR (4), A SUBDIVISION IN HARRIS ow COUNTY, TEXAS",
      "prop_address": "407 DEIRDRE ANNE DR",
      "prop_city": "HOUSTON",
      "prop_state": "TX",
      "prop_zip": "77088",
      "match_confidence": "high",
      "hcad_url": "",
      "clerk_url": "https://www.cclerk.hctx.net/applications/websearch/ViewECdocs.aspx?ID=bWXqGXasMeuE7YZXR3B2NUNXeLVZTKlhHSbKofnpRC5vluoLDcv/8FH2TlIzxHdFjRAFbgHxERv1vrsAbPPbByL0LLM8sTLWaGVLxnW/N7PUt0LsQpLu1QrxJGQkzhmd",
      "needs_ocr": false
    },
    {
      "doc_id": "FRCL-2026-1414",
      "doc_type": "FRCL",
      "cat": "FORECLOSURE",
      "cat_label": "Foreclosure Posting",
      "sale_date": "05/05/2026",
      "file_date": "02/26/2026",
      "date_scraped": "2026-04-13",
      "batch_id": "B2",
      "batch_label": "Batch 2 \u2014 2026-04-13 12:25 PM",
      "grantor": "",
      "co_borrower": "",
      "amount": "",
      "mortgagee": "",
      "legal_description": "LOT FORTY-TWO (42), BLOCK ONE (1), OF RABURN RESERVE SEC. 1, A SUBDIVISION IN HARRIQ\\COUNTY, TEXAS",
      "prop_address": "Not found",
      "prop_city": "",
      "prop_state": "TX",
      "prop_zip": "",
      "match_confidence": "none",
      "hcad_url": "",
      "clerk_url": "https://www.cclerk.hctx.net/applications/websearch/ViewECdocs.aspx?ID=bWXqGXasMeuE7YZXR3B2NUNXeLVZTKlhHSbKofnpRC553Z6OQ4rslkKOw+I0TIa3zvJ1KCu2HpfqrYHicNzLq9RtFWJbgvAIVFDFBHpR/9Bh9sHEHxQYVbb6LIc4SLQr",
      "needs_ocr": false
    }
  ]
}